bytehouse_sqlalchemy/__init__.py
bytehouse_sqlalchemy/exceptions.py
bytehouse_sqlalchemy/alembic/__init__.py
bytehouse_sqlalchemy/alembic/comparators.py
bytehouse_sqlalchemy/alembic/dialect.py
bytehouse_sqlalchemy/alembic/operations.py
bytehouse_sqlalchemy/alembic/renderers.py
bytehouse_sqlalchemy/alembic/toimpl.py
bytehouse_sqlalchemy/drivers/__init__.py
bytehouse_sqlalchemy/drivers/base.py
bytehouse_sqlalchemy/drivers/reflection.py
bytehouse_sqlalchemy/drivers/compilers/__init__.py
bytehouse_sqlalchemy/drivers/compilers/ddlcompiler.py
bytehouse_sqlalchemy/drivers/compilers/sqlcompiler.py
bytehouse_sqlalchemy/drivers/compilers/typecompiler.py
bytehouse_sqlalchemy/drivers/native/__init__.py
bytehouse_sqlalchemy/drivers/native/base.py
bytehouse_sqlalchemy/drivers/native/connector.py
bytehouse_sqlalchemy/engines/__init__.py
bytehouse_sqlalchemy/engines/base.py
bytehouse_sqlalchemy/engines/cnchmergetree.py
bytehouse_sqlalchemy/engines/misc.py
bytehouse_sqlalchemy/engines/replicated.py
bytehouse_sqlalchemy/engines/util.py
bytehouse_sqlalchemy/ext/__init__.py
bytehouse_sqlalchemy/ext/clauses.py
bytehouse_sqlalchemy/ext/declarative.py
bytehouse_sqlalchemy/orm/__init__.py
bytehouse_sqlalchemy/orm/query.py
bytehouse_sqlalchemy/orm/session.py
bytehouse_sqlalchemy/sql/__init__.py
bytehouse_sqlalchemy/sql/ddl.py
bytehouse_sqlalchemy/sql/schema.py
bytehouse_sqlalchemy/sql/selectable.py
bytehouse_sqlalchemy/types/__init__.py
bytehouse_sqlalchemy/types/common.py
bytehouse_sqlalchemy/types/ip.py
bytehouse_sqlalchemy/types/nested.py
bytehouse_sqlalchemy-1.0.2.dist-info/LICENSE
bytehouse_sqlalchemy-1.0.2.dist-info/METADATA
bytehouse_sqlalchemy-1.0.2.dist-info/WHEEL
bytehouse_sqlalchemy-1.0.2.dist-info/entry_points.txt
bytehouse_sqlalchemy-1.0.2.dist-info/top_level.txt
bytehouse_sqlalchemy-1.0.2.dist-info/RECORD
