Metadata-Version: 2.1
Name: bytehouse-sqlalchemy
Version: 1.0.2
Summary: ByteHouse SQLAlchemy Dialect
Home-page: https://github.com/bytehouse-cloud/bytehouse-sqlalchemy
Author: Rafsan Mazumder
Author-email: rafsan.mazumder@bytedance.com
License: MIT
Project-URL: Documentation, https://github.com/bytehouse-cloud/bytehouse-sqlalchemy
Project-URL: Changes, https://github.com/bytehouse-cloud/bytehouse-sqlalchemy/blob/master/CHANGELOG.md
Keywords: ByteHouse db database cloud analytics
Classifier: Development Status :: 4 - Beta
Classifier: Environment :: Console
Classifier: Intended Audience :: Developers
Classifier: Intended Audience :: Information Technology
Classifier: License :: OSI Approved :: MIT License
Classifier: Operating System :: OS Independent
Classifier: Programming Language :: SQL
Classifier: Programming Language :: Python :: 3
Classifier: Programming Language :: Python :: 3.6
Classifier: Programming Language :: Python :: 3.7
Classifier: Programming Language :: Python :: 3.8
Classifier: Programming Language :: Python :: 3.9
Classifier: Programming Language :: Python :: 3.10
Classifier: Topic :: Database
Classifier: Topic :: Software Development
Classifier: Topic :: Software Development :: Libraries
Classifier: Topic :: Software Development :: Libraries :: Application Frameworks
Classifier: Topic :: Software Development :: Libraries :: Python Modules
Classifier: Topic :: Scientific/Engineering :: Information Analysis
Requires-Python: >=3.6, <4
License-File: LICENSE
Requires-Dist: bytehouse-driver (==1.0.2)
Requires-Dist: sqlalchemy (<1.5,>=1.4)
Requires-Dist: requests
